pytempmailsapi/__init__.py
py_temp_mails_api-1.3.dist-info/METADATA
py_temp_mails_api-1.3.dist-info/WHEEL
py_temp_mails_api-1.3.dist-info/top_level.txt
py_temp_mails_api-1.3.dist-info/RECORD
