Metadata-Version: 2.1
Name: py-temp-mails-api
Version: 1.3
Summary: pyTempMailsApi is a library that allows you to easily interact with the site https://temp-mail.org/
Home-page: https://github.com/onigirisell/pyTempMailsApi
Author: Fitrad3w
Author-email: onigirisell@protonmail.com
Classifier: Programming Language :: Python :: 3
Classifier: License :: OSI Approved :: MIT License
Classifier: Operating System :: OS Independent
Requires-Python: >=3.6
Requires-Dist: grequests
Requires-Dist: requests
